fastybird_ws_server_plugin/__init__.py
fastybird_ws_server_plugin/bootstrap.py
fastybird_ws_server_plugin/client.py
fastybird_ws_server_plugin/clients.py
fastybird_ws_server_plugin/events.py
fastybird_ws_server_plugin/exceptions.py
fastybird_ws_server_plugin/logger.py
fastybird_ws_server_plugin/publisher.py
fastybird_ws_server_plugin/py.typed
fastybird_ws_server_plugin/server.py
fastybird_ws_server_plugin/types.py
tests/__init__.py
tests/pytests/__init__.py
fastybird_ws_server_plugin-0.13.0.dist-info/LICENSE.md
fastybird_ws_server_plugin-0.13.0.dist-info/METADATA
fastybird_ws_server_plugin-0.13.0.dist-info/WHEEL
fastybird_ws_server_plugin-0.13.0.dist-info/top_level.txt
fastybird_ws_server_plugin-0.13.0.dist-info/RECORD
