Metadata-Version: 2.1
Name: fastybird-ws-server-plugin
Version: 0.13.0
Summary: FastyBird WS server plugin
Home-page: https://github.com/FastyBird/ws-server-plugin
Author: FastyBird
Author-email: code@fastybird.com
License: Apache Software License (Apache Software License 2.0)
Download-URL: https://github.com/FastyBird/ws-server-plugin/archive/0.13.0.tar.gz
Platform: UNKNOWN
Classifier: Development Status :: 3 - Alpha
Classifier: Environment :: Plugins
Classifier: Intended Audience :: Developers
Classifier: Intended Audience :: Education
Classifier: Intended Audience :: Information Technology
Classifier: License :: OSI Approved :: Apache Software License
Classifier: Operating System :: OS Independent
Classifier: Programming Language :: Python
Classifier: Programming Language :: Python :: 3.7
Classifier: Programming Language :: Python :: 3.8
Classifier: Programming Language :: Python :: 3.9
Classifier: Programming Language :: Python :: 3.10
Classifier: Programming Language :: Python :: 3 :: Only
Classifier: Topic :: Communications
Classifier: Topic :: Home Automation
Classifier: Topic :: System :: Hardware
Requires-Python: >=3.7
License-File: LICENSE.md
Requires-Dist: fastybird-metadata
Requires-Dist: kink
Requires-Dist: setuptools
Requires-Dist: whistle
